README.md
setup.cfg
setup.py
mathviz_hopper/__init__.py
mathviz_hopper.egg-info/PKG-INFO
mathviz_hopper.egg-info/SOURCES.txt
mathviz_hopper.egg-info/dependency_links.txt
mathviz_hopper.egg-info/top_level.txt
mathviz_hopper/src/Scatter.py
mathviz_hopper/src/Untitled.ipynb
mathviz_hopper/src/__init__.py
mathviz_hopper/src/bottle.py
mathviz_hopper/src/constants.py
mathviz_hopper/src/cuts.txt
mathviz_hopper/src/data
mathviz_hopper/src/helpers.py
mathviz_hopper/src/indices.py
mathviz_hopper/src/math_list.py
mathviz_hopper/src/print_math.py
mathviz_hopper/src/server.py
mathviz_hopper/src/server_helpers.py
mathviz_hopper/src/table.py
mathviz_hopper/src/data/print_math
mathviz_hopper/src/data/table
mathviz_hopper/src/data/print_math/bundle.js
mathviz_hopper/src/data/print_math/katex.css
mathviz_hopper/src/data/print_math/notebook_index.html
mathviz_hopper/src/data/print_math/standalone_index.html
mathviz_hopper/src/data/print_math/fonts/KaTeX_AMS-Regular.eot
mathviz_hopper/src/data/print_math/fonts/KaTeX_AMS-Regular.ttf
mathviz_hopper/src/data/print_math/fonts/KaTeX_AMS-Regular.woff
mathviz_hopper/src/data/print_math/fonts/KaTeX_AMS-Regular.woff2
mathviz_hopper/src/data/print_math/fonts/KaTeX_Caligraphic-Bold.eot
mathviz_hopper/src/data/print_math/fonts/KaTeX_Caligraphic-Bold.ttf
mathviz_hopper/src/data/print_math/fonts/KaTeX_Caligraphic-Bold.woff
mathviz_hopper/src/data/print_math/fonts/KaTeX_Caligraphic-Bold.woff2
mathviz_hopper/src/data/print_math/fonts/KaTeX_Caligraphic-Regular.eot
mathviz_hopper/src/data/print_math/fonts/KaTeX_Caligraphic-Regular.ttf
mathviz_hopper/src/data/print_math/fonts/KaTeX_Caligraphic-Regular.woff
mathviz_hopper/src/data/print_math/fonts/KaTeX_Caligraphic-Regular.woff2
mathviz_hopper/src/data/print_math/fonts/KaTeX_Fraktur-Bold.eot
mathviz_hopper/src/data/print_math/fonts/KaTeX_Fraktur-Bold.ttf
mathviz_hopper/src/data/print_math/fonts/KaTeX_Fraktur-Bold.woff
mathviz_hopper/src/data/print_math/fonts/KaTeX_Fraktur-Bold.woff2
mathviz_hopper/src/data/print_math/fonts/KaTeX_Fraktur-Regular.eot
mathviz_hopper/src/data/print_math/fonts/KaTeX_Fraktur-Regular.ttf
