Metadata-Version: 1.1
Name: mathviz-hopper
Version: 0.3.1
Summary: A word vector visualization library
Home-page: https://github.com/samghelms/mathviz
Author: Samuel Helms
Author-email: samuel.helms@yale.edu
License: UNKNOWN
Download-URL: https://github.com/samghelms/mathviz/archive/0.2.tar.gz
Platform: UNKNOWN
